openbus_light/__init__.py
openbus_light/utils.py
openbus_light/manipulate/__init__.py
openbus_light/manipulate/demand.py
openbus_light/manipulate/direction.py
openbus_light/manipulate/line.py
openbus_light/manipulate/paths.py
openbus_light/manipulate/point.py
openbus_light/manipulate/recorded_trip.py
openbus_light/manipulate/scenario.py
openbus_light/manipulate/station.py
openbus_light/manipulate/walkable_distance.py
openbus_light/model/__init__.py
openbus_light/model/demand.py
openbus_light/model/direction.py
openbus_light/model/district.py
openbus_light/model/line.py
openbus_light/model/point.py
openbus_light/model/recordedtrip.py
openbus_light/model/scenario.py
openbus_light/model/station.py
openbus_light/model/type.py
openbus_light/model/walkable_distance.py
openbus_light/plan/__init__.py
openbus_light/plan/network.py
openbus_light/plan/parameters.py
openbus_light/plan/problem.py
openbus_light/plan/result.py
openbus_light/plan/summary.py
openbus_light/plot/__init__.py
openbus_light/plot/_background.py
openbus_light/plot/_cmap.py
openbus_light/plot/_convert.py
openbus_light/plot/demand.py
openbus_light/plot/line.py
openbus_light/plot/line_usage.py
openbus_light/plot/network.py
openbus_light-0.4.0.dist-info/METADATA
openbus_light-0.4.0.dist-info/WHEEL
openbus_light-0.4.0.dist-info/licenses/LICENCE
openbus_light-0.4.0.dist-info/RECORD
