Metadata-Version: 2.4
Name: openbus_light
Version: 0.4.0
Summary: Code for PuV TS-PART
Project-URL: Homepage, https://www.ivt.ethz.ch/
Author-email: "Daniel Heimgartner, Florian Fuchs, Thomas Dubach" <daniel.heimgartner@ivt.baug.ethz.ch>
License-File: LICENCE
Classifier: License :: OSI Approved :: MIT License
Classifier: Operating System :: OS Independent
Classifier: Programming Language :: Python :: 3
Requires-Python: >=3.10
Requires-Dist: matplotlib~=3.10.1
Requires-Dist: numba~=0.61.0
Requires-Dist: numpy~=2.1.3
Requires-Dist: pandas~=2.2.3
Requires-Dist: plotly~=6.0.0
Requires-Dist: pulp~=3.1.1
Requires-Dist: python-igraph~=0.11.8
Requires-Dist: tqdm~=4.66.6
